{
  "db_name": "SQLite",
  "query": "select * from recipes where id = $1",
  "describe": {
    "columns": [
      {
        "name": "id",
        "ordinal": 0,
        "type_info": "Text"
      },
      {
        "name": "item_id",
        "ordinal": 1,
        "type_info": "Text"
      },
      {
        "name": "output_amount",
        "ordinal": 2,
        "type_info": "Integer"
      }
    ],
    "parameters": {
      "Right": 1
    },
    "nullable": [
      false,
      false,
      false
    ]
  },
  "hash": "c1ef51010171d0b4854c1807613a9cc43581cd765c5c05fd2ede5bd4fe65f330"
}
