{
  "db_name": "SQLite",
  "query": "INSERT INTO games (id, name, description, picture) VALUES ($1, $2, $3, $4) RETURNING id, name, description, picture",
  "describe": {
    "columns": [
      {
        "name": "id",
        "ordinal": 0,
        "type_info": "Text"
      },
      {
        "name": "name",
        "ordinal": 1,
        "type_info": "Text"
      },
      {
        "name": "description",
        "ordinal": 2,
        "type_info": "Text"
      },
      {
        "name": "picture",
        "ordinal": 3,
        "type_info": "Text"
      }
    ],
    "parameters": {
      "Right": 4
    },
    "nullable": [
      false,
      false,
      false,
      true
    ]
  },
  "hash": "10a3649030f067940a7f62d166662bc652730ea5e598d80934aba2f397e0762f"
}
